segmenthee/__init__.py
segmenthee/cart_api.py
segmenthee/config.py
segmenthee/parser_api.py
segmenthee/shop.py
segmentheepy_prak-1.0.1.dist-info/METADATA
segmentheepy_prak-1.0.1.dist-info/WHEEL
segmentheepy_prak-1.0.1.dist-info/top_level.txt
segmentheepy_prak-1.0.1.dist-info/RECORD
