Metadata-Version: 2.1
Name: segmentheepy-prak
Version: 1.0.1
Summary: Segmenthee library
Author: Drávai Tamás
License: MIT
Requires-Python: >=3.8
Requires-Dist: user-agents (==2.2.0)
Requires-Dist: xgboost (==1.7.3)
Requires-Dist: scikit-learn (==0.24.2)
